styled_log.py
styled_log-1.0.dist-info/METADATA
styled_log-1.0.dist-info/RECORD
styled_log-1.0.dist-info/WHEEL
styled_log-1.0.dist-info/top_level.txt
