Metadata-Version: 2.1
Name: styled-log
Version: 1.0
Summary: logging.Formatter allowing for customized and colored logging output.
Home-page: https://gitlab.com/ittVannak/styled-log
Author: Nicholas Lawrence
Author-email: nickclawrence@gmail.com
License: MIT
Platform: UNKNOWN
Classifier: Intended Audience :: Developers
Classifier: Natural Language :: English
Classifier: License :: OSI Approved :: MIT License
Classifier: Operating System :: OS Independent
Classifier: Programming Language :: Python
Classifier: Programming Language :: Python :: 3.6
Classifier: Topic :: Software Development :: Libraries :: Python Modules
Requires-Dist: colorama
